telegram_menu_builder/__init__.py
telegram_menu_builder/builder.py
telegram_menu_builder/encoding.py
telegram_menu_builder/py.typed
telegram_menu_builder/router.py
telegram_menu_builder/types.py
telegram_menu_builder/storage/__init__.py
telegram_menu_builder/storage/base.py
telegram_menu_builder/storage/memory.py
telegram_menu_builder-0.1.1.dist-info/licenses/LICENSE
telegram_menu_builder-0.1.1.dist-info/METADATA
telegram_menu_builder-0.1.1.dist-info/WHEEL
telegram_menu_builder-0.1.1.dist-info/top_level.txt
telegram_menu_builder-0.1.1.dist-info/RECORD
