Metadata-Version: 2.4
Name: telegram-menu-builder
Version: 0.1.1
Summary: A powerful builder library for creating recursive inline keyboard menus in python-telegram-bot
Author-email: Simone Flavio Paris <info@sf-paris.dev>
License-Expression: MIT
Project-URL: Homepage, https://github.com/smoxy/telegram-menu-builder
Project-URL: Documentation, https://telegram-menu-builder.readthedocs.io
Project-URL: Repository, https://github.com/smoxy/telegram-menu-builder
Project-URL: Bug Tracker, https://github.com/smoxy/telegram-menu-builder/issues
Keywords: telegram,bot,inline-keyboard,menu,builder,python-telegram-bot
Classifier: Development Status :: 3 - Alpha
Classifier: Intended Audience :: Developers
Classifier: Programming Language :: Python :: 3
Classifier: Programming Language :: Python :: 3.12
Classifier: Framework :: AsyncIO
Classifier: Topic :: Communications :: Chat
Classifier: Topic :: Software Development :: Libraries :: Python Modules
Classifier: Typing :: Typed
Requires-Python: >=3.12
License-File: LICENSE
Requires-Dist: python-telegram-bot<22.6,>=20.0
Requires-Dist: pydantic<3.0,>=2.0
Provides-Extra: dev
Requires-Dist: pytest>=8.0; extra == "dev"
Requires-Dist: pytest-asyncio>=0.23; extra == "dev"
Requires-Dist: pytest-cov>=4.1; extra == "dev"
Requires-Dist: pytest-mock>=3.12; extra == "dev"
Requires-Dist: mypy>=1.8; extra == "dev"
Requires-Dist: pyright>=1.1.350; extra == "dev"
Requires-Dist: ruff>=0.2.0; extra == "dev"
Requires-Dist: black>=24.0; extra == "dev"
Requires-Dist: pre-commit>=3.6; extra == "dev"
Provides-Extra: redis
Requires-Dist: redis>=5.0; extra == "redis"
Provides-Extra: sql
Requires-Dist: sqlalchemy>=2.0; extra == "sql"
Requires-Dist: aiosqlite>=0.19; extra == "sql"
Provides-Extra: all
Requires-Dist: telegram-menu-builder[redis,sql]; extra == "all"
Dynamic: license-file
